Workbook

Sheet Summary
B2: Amazon seller report
B3: ="Last "&Settings!B1&" days, as of "&TEXT(Settings!B2,"mmm d, yyyy")
B5: Revenue | D5: Net profit | F5: Margin | H5: Ad spend | J5: TACoS | L5: SKUs to reorder now
B6: ='Profit by SKU'!E14 | D6: ='Profit by SKU'!M14 | F6: ='Profit by SKU'!N14 | H6: ='Profit by SKU'!I14 | J6: ='Profit by SKU'!Q14 | L6: =COUNTIF('Restock plan'!L2:L13,"ORDER NOW*")
B9: Needs attention
B10: Stockout risk | C10: HP-GLS-JAR4 | E10: FBA stock lasts ~9 days, reorder lead time is 50 days. Order now.
B11: Reorder soon | C11: HP-BAM-CB3 | E11: ~60 days of stock incl. inbound; place the next order within 1 days.
B12: Reorder soon | C12: HP-DSH-RCK | E12: ~76 days of stock incl. inbound; place the next order within 7 days.
B13: Reorder soon | C13: HP-KNF-MAG | E13: ~57 days of stock incl. inbound; place the next order today.
B14: Losing money | C14: HP-CRM-MUG2 | E14: Net -$98 this period; ad spend $260 (TACoS 16%).
B15: Losing money | C15: HP-HRB-KEEP | E15: Net -$137 this period; ad spend $690 (TACoS 36%).
B16: Low conversion | C16: HP-BEE-WRP | E16: 5.7% of 3,655 sessions buy. Check price, images, reviews.
B17: Low conversion | C17: HP-DSH-RCK | E17: 2.5% of 5,000 sessions buy. Check price, images, reviews.
B18: Low conversion | C18: HP-CRM-MUG2 | E18: 2.8% of 2,720 sessions buy. Check price, images, reviews.
B19: Low conversion | C19: HP-HRB-KEEP | E19: 2.8% of 3,639 sessions buy. Check price, images, reviews.
B20: Overstock | C20: HP-CRM-MUG2 | E20: 355 days of stock: storage fees add up. Consider a promotion.
B21: Overstock | C21: HP-HRB-KEEP | E21: 210 days of stock: storage fees add up. Consider a promotion.

Sheet Profit by SKU
A1: SKU | B1: Product | C1: Sessions | D1: Units | E1: Revenue | F1: Referral % | G1: FBA fee / unit | H1: COGS / unit | I1: PPC spend | J1: PPC sales | K1: Amazon fees | L1: COGS | M1: Net profit | N1: Margin | O1: Profit / unit | P1: ACoS | Q1: TACoS | R1: Conversion
A2: HP-BAM-CB3 | B2: Bamboo Cutting Board Set, 3-Piece with Juice Groove | C2: 2779 | D2: 389 | E2: 12466.43 | F2: 0.15 | G2: 6.45 | H2: 8.3 | I2: 980 | J2: 3900 | K2: =E2*F2+D2*G2 | L2: =D2*H2 | M2: =E2-K2-L2-I2 | N2: =IFERROR(M2/E2,0) | O2: =IFERROR(M2/D2,0) | P2: =IFERROR(I2/J2,0) | Q2: =IFERROR(I2/E2,0) | R2: =IFERROR(D2/C2,0)
A3: HP-SIL-LID6 | B3: Silicone Stretch Lids, 6-Pack Assorted Sizes | C3: 5119 | D3: 728 | E3: 10182.78 | F3: 0.15 | G3: 3.86 | H3: 2.5 | I3: 1150 | J3: 6200 | K3: =E3*F3+D3*G3 | L3: =D3*H3 | M3: =E3-K3-L3-I3 | N3: =IFERROR(M3/E3,0) | O3: =IFERROR(M3/D3,0) | P3: =IFERROR(I3/J3,0) | Q3: =IFERROR(I3/E3,0) | R3: =IFERROR(D3/C3,0)
A4: HP-MSR-SET | B4: Magnetic Measuring Spoons Set of 8 | C4: 2298 | D4: 305 | E4: 5039.24 | F4: 0.15 | G4: 3.86 | H4: 3.6 | I4: 310 | J4: 2100 | K4: =E4*F4+D4*G4 | L4: =D4*H4 | M4: =E4-K4-L4-I4 | N4: =IFERROR(M4/E4,0) | O4: =IFERROR(M4/D4,0) | P4: =IFERROR(I4/J4,0) | Q4: =IFERROR(I4/E4,0) | R4: =IFERROR(D4/C4,0)
A5: HP-SS-STRW8 | B5: Stainless Steel Straws, 8-Pack with Brushes | C5: 4456 | D5: 558 | E5: 5218.32 | F5: 0.15 | G5: 3.22 | H5: 1.6 | I5: 420 | J5: 2900 | K5: =E5*F5+D5*G5 | L5: =D5*H5 | M5: =E5-K5-L5-I5 | N5: =IFERROR(M5/E5,0) | O5: =IFERROR(M5/D5,0) | P5: =IFERROR(I5/J5,0) | Q5: =IFERROR(I5/E5,0) | R5: =IFERROR(D5/C5,0)
A6: HP-BEE-WRP | B6: Beeswax Food Wraps, 9-Pack | C6: 3655 | D6: 209 | E6: 3805.68 | F6: 0.15 | G6: 3.86 | H6: 4.3 | I6: 520 | J6: 1400 | K6: =E6*F6+D6*G6 | L6: =D6*H6 | M6: =E6-K6-L6-I6 | N6: =IFERROR(M6/E6,0) | O6: =IFERROR(M6/D6,0) | P6: =IFERROR(I6/J6,0) | Q6: =IFERROR(I6/E6,0) | R6: =IFERROR(D6/C6,0)
A7: HP-OIL-SPR | B7: Olive Oil Sprayer for Cooking, 7oz Glass | C7: 4053 | D7: 352 | E7: 4617.2 | F7: 0.15 | G7: 3.86 | H7: 3.3 | I7: 520 | J7: 2700 | K7: =E7*F7+D7*G7 | L7: =D7*H7 | M7: =E7-K7-L7-I7 | N7: =IFERROR(M7/E7,0) | O7: =IFERROR(M7/D7,0) | P7: =IFERROR(I7/J7,0) | Q7: =IFERROR(I7/E7,0) | R7: =IFERROR(D7/C7,0)
A8: HP-KNF-MAG | B8: Magnetic Knife Strip 16 inch, Walnut | C8: 1307 | D8: 122 | E8: 3558.04 | F8: 0.15 | G8: 6.45 | H8: 9.5 | I8: 210 | J8: 1100 | K8: =E8*F8+D8*G8 | L8: =D8*H8 | M8: =E8-K8-L8-I8 | N8: =IFERROR(M8/E8,0) | O8: =IFERROR(M8/D8,0) | P8: =IFERROR(I8/J8,0) | Q8: =IFERROR(I8/E8,0) | R8: =IFERROR(D8/C8,0)
A9: HP-SPC-RCK | B9: Rotating Spice Rack Organizer, 2-Tier | C9: 1975 | D9: 150 | E9: 3641.44 | F9: 0.15 | G9: 6.98 | H9: 8.7 | I9: 300 | J9: 1500 | K9: =E9*F9+D9*G9 | L9: =D9*H9 | M9: =E9-K9-L9-I9 | N9: =IFERROR(M9/E9,0) | O9: =IFERROR(M9/D9,0) | P9: =IFERROR(I9/J9,0) | Q9: =IFERROR(I9/E9,0) | R9: =IFERROR(D9/C9,0)
A10: HP-DSH-RCK | B10: Over-the-Sink Dish Drying Rack, Adjustable | C10: 5000 | D10: 127 | E10: 4803.61 | F10: 0.15 | G10: 9.41 | H10: 16.3 | I10: 440 | J10: 1800 | K10: =E10*F10+D10*G10 | L10: =D10*H10 | M10: =E10-K10-L10-I10 | N10: =IFERROR(M10/E10,0) | O10: =IFERROR(M10/D10,0) | P10: =IFERROR(I10/J10,0) | Q10: =IFERROR(I10/E10,0) | R10: =IFERROR(D10/C10,0)
A11: HP-GLS-JAR4 | B11: Glass Mason Jars 32oz, Set of 4 with Lids | C11: 2111 | D11: 235 | E11: 6344.17 | F11: 0.15 | G11: 7.92 | H11: 11 | I11: 610 | J11: 1900 | K11: =E11*F11+D11*G11 | L11: =D11*H11 | M11: =E11-K11-L11-I11 | N11: =IFERROR(M11/E11,0) | O11: =IFERROR(M11/D11,0) | P11: =IFERROR(I11/J11,0) | Q11: =IFERROR(I11/E11,0) | R11: =IFERROR(D11/C11,0)
A12: HP-CRM-MUG2 | B12: Ceramic Coffee Mugs 16oz, Set of 2 | C12: 2720 | D12: 76 | E12: 1667.32 | F12: 0.15 | G12: 7.92 | H12: 8.6 | I12: 260 | J12: 520 | K12: =E12*F12+D12*G12 | L12: =D12*H12 | M12: =E12-K12-L12-I12 | N12: =IFERROR(M12/E12,0) | O12: =IFERROR(M12/D12,0) | P12: =IFERROR(I12/J12,0) | Q12: =IFERROR(I12/E12,0) | R12: =IFERROR(D12/C12,0)
A13: HP-HRB-KEEP | B13: Herb Keeper Fresh Saver, Clear | C13: 3639 | D13: 103 | E13: 1935.41 | F13: 0.15 | G13: 5.1 | H13: 5.5 | I13: 690 | J13: 980 | K13: =E13*F13+D13*G13 | L13: =D13*H13 | M13: =E13-K13-L13-I13 | N13: =IFERROR(M13/E13,0) | O13: =IFERROR(M13/D13,0) | P13: =IFERROR(I13/J13,0) | Q13: =IFERROR(I13/E13,0) | R13: =IFERROR(D13/C13,0)
A14: Total | C14: =SUM(C2:C13) | D14: =SUM(D2:D13) | E14: =SUM(E2:E13) | I14: =SUM(I2:I13) | J14: =SUM(J2:J13) | K14: =SUM(K2:K13) | L14: =SUM(L2:L13) | M14: =SUM(M2:M13) | N14: =IFERROR(M14/E14,0) | O14: =IFERROR(M14/D14,0) | P14: =IFERROR(I14/J14,0) | Q14: =IFERROR(I14/E14,0) | R14: =IFERROR(D14/C14,0)

Sheet Restock plan
A1: SKU | B1: Product | C1: Units / day | D1: FBA fulfillable | E1: Inbound | F1: Days of cover (FBA) | G1: Days of cover (incl. inbound) | H1: Lead time, days | I1: Runs out (FBA) | J1: Order by (incl. inbound) | K1: Suggested order qty | L1: Status
A2: HP-GLS-JAR4 | B2: Glass Mason Jars 32oz, Set of 4 with Lids | C2: ='Profit by SKU'!D11/Settings!$B$1 | D2: 70 | E2: 300 | F2: =IFERROR(D2/C2,999) | G2: =IFERROR((D2+E2)/C2,999) | H2: 50 | I2: =IFERROR(Settings!$B$2+D2/C2,"") | J2: =IFERROR(MAX(Settings!$B$2,Settings!$B$2+G2-H2-Settings!$B$3),"") | K2: =IF(OR(LEFT(L2,9)="ORDER NOW",L2="Order this week"),MAX(0,CEILING((H2+Settings!$B$3+Settings!$B$4)*C2-D2-E2,10)),0) | L2: =IF(G2-H2-Settings!$B$3<=0,IF(F2<H2,"ORDER NOW: stockout risk","ORDER NOW"),IF(G2-H2-Settings!$B$3<=7,"Order this week",IF(G2>Settings!$B$5,"Overstock",IF(F2<H2,"Low FBA, inbound covers","OK"))))
A3: HP-BAM-CB3 | B3: Bamboo Cutting Board Set, 3-Piece with Juice Groove | C3: ='Profit by SKU'!D2/Settings!$B$1 | D3: 180 | E3: 600 | F3: =IFERROR(D3/C3,999) | G3: =IFERROR((D3+E3)/C3,999) | H3: 45 | I3: =IFERROR(Settings!$B$2+D3/C3,"") | J3: =IFERROR(MAX(Settings!$B$2,Settings!$B$2+G3-H3-Settings!$B$3),"") | K3: =IF(OR(LEFT(L3,9)="ORDER NOW",L3="Order this week"),MAX(0,CEILING((H3+Settings!$B$3+Settings!$B$4)*C3-D3-E3,10)),0) | L3: =IF(G3-H3-Settings!$B$3<=0,IF(F3<H3,"ORDER NOW: stockout risk","ORDER NOW"),IF(G3-H3-Settings!$B$3<=7,"Order this week",IF(G3>Settings!$B$5,"Overstock",IF(F3<H3,"Low FBA, inbound covers","OK"))))
A4: HP-DSH-RCK | B4: Over-the-Sink Dish Drying Rack, Adjustable | C4: ='Profit by SKU'!D10/Settings!$B$1 | D4: 120 | E4: 200 | F4: =IFERROR(D4/C4,999) | G4: =IFERROR((D4+E4)/C4,999) | H4: 55 | I4: =IFERROR(Settings!$B$2+D4/C4,"") | J4: =IFERROR(MAX(Settings!$B$2,Settings!$B$2+G4-H4-Settings!$B$3),"") | K4: =IF(OR(LEFT(L4,9)="ORDER NOW",L4="Order this week"),MAX(0,CEILING((H4+Settings!$B$3+Settings!$B$4)*C4-D4-E4,10)),0) | L4: =IF(G4-H4-Settings!$B$3<=0,IF(F4<H4,"ORDER NOW: stockout risk","ORDER NOW"),IF(G4-H4-Settings!$B$3<=7,"Order this week",IF(G4>Settings!$B$5,"Overstock",IF(F4<H4,"Low FBA, inbound covers","OK"))))
A5: HP-BEE-WRP | B5: Beeswax Food Wraps, 9-Pack | C5: ='Profit by SKU'!D6/Settings!$B$1 | D5: 300 | E5: 400 | F5: =IFERROR(D5/C5,999) | G5: =IFERROR((D5+E5)/C5,999) | H5: 40 | I5: =IFERROR(Settings!$B$2+D5/C5,"") | J5: =IFERROR(MAX(Settings!$B$2,Settings!$B$2+G5-H5-Settings!$B$3),"") | K5: =IF(OR(LEFT(L5,9)="ORDER NOW",L5="Order this week"),MAX(0,CEILING((H5+Settings!$B$3+Settings!$B$4)*C5-D5-E5,10)),0) | L5: =IF(G5-H5-Settings!$B$3<=0,IF(F5<H5,"ORDER NOW: stockout risk","ORDER NOW"),IF(G5-H5-Settings!$B$3<=7,"Order this week",IF(G5>Settings!$B$5,"Overstock",IF(F5<H5,"Low FBA, inbound covers","OK"))))
A6: HP-KNF-MAG | B6: Magnetic Knife Strip 16 inch, Walnut | C6: ='Profit by SKU'!D8/Settings!$B$1 | D6: 230 | E6: 0 | F6: =IFERROR(D6/C6,999) | G6: =IFERROR((D6+E6)/C6,999) | H6: 50 | I6: =IFERROR(Settings!$B$2+D6/C6,"") | J6: =IFERROR(MAX(Settings!$B$2,Settings!$B$2+G6-H6-Settings!$B$3),"") | K6: =IF(OR(LEFT(L6,9)="ORDER NOW",L6="Order this week"),MAX(0,CEILING((H6+Settings!$B$3+Settings!$B$4)*C6-D6-E6,10)),0) | L6: =IF(G6-H6-Settings!$B$3<=0,IF(F6<H6,"ORDER NOW: stockout risk","ORDER NOW"),IF(G6-H6-Settings!$B$3<=7,"Order this week",IF(G6>Settings!$B$5,"Overstock",IF(F6<H6,"Low FBA, inbound covers","OK"))))
A7: HP-SPC-RCK | B7: Rotating Spice Rack Organizer, 2-Tier | C7: ='Profit by SKU'!D9/Settings!$B$1 | D7: 410 | E7: 0 | F7: =IFERROR(D7/C7,999) | G7: =IFERROR((D7+E7)/C7,999) | H7: 50 | I7: =IFERROR(Settings!$B$2+D7/C7,"") | J7: =IFERROR(MAX(Settings!$B$2,Settings!$B$2+G7-H7-Settings!$B$3),"") | K7: =IF(OR(LEFT(L7,9)="ORDER NOW",L7="Order this week"),MAX(0,CEILING((H7+Settings!$B$3+Settings!$B$4)*C7-D7-E7,10)),0) | L7: =IF(G7-H7-Settings!$B$3<=0,IF(F7<H7,"ORDER NOW: stockout risk","ORDER NOW"),IF(G7-H7-Settings!$B$3<=7,"Order this week",IF(G7>Settings!$B$5,"Overstock",IF(F7<H7,"Low FBA, inbound covers","OK"))))
A8: HP-MSR-SET | B8: Magnetic Measuring Spoons Set of 8 | C8: ='Profit by SKU'!D4/Settings!$B$1 | D8: 950 | E8: 0 | F8: =IFERROR(D8/C8,999) | G8: =IFERROR((D8+E8)/C8,999) | H8: 40 | I8: =IFERROR(Settings!$B$2+D8/C8,"") | J8: =IFERROR(MAX(Settings!$B$2,Settings!$B$2+G8-H8-Settings!$B$3),"") | K8: =IF(OR(LEFT(L8,9)="ORDER NOW",L8="Order this week"),MAX(0,CEILING((H8+Settings!$B$3+Settings!$B$4)*C8-D8-E8,10)),0) | L8: =IF(G8-H8-Settings!$B$3<=0,IF(F8<H8,"ORDER NOW: stockout risk","ORDER NOW"),IF(G8-H8-Settings!$B$3<=7,"Order this week",IF(G8>Settings!$B$5,"Overstock",IF(F8<H8,"Low FBA, inbound covers","OK"))))
A9: HP-OIL-SPR | B9: Olive Oil Sprayer for Cooking, 7oz Glass | C9: ='Profit by SKU'!D7/Settings!$B$1 | D9: 1100 | E9: 0 | F9: =IFERROR(D9/C9,999) | G9: =IFERROR((D9+E9)/C9,999) | H9: 35 | I9: =IFERROR(Settings!$B$2+D9/C9,"") | J9: =IFERROR(MAX(Settings!$B$2,Settings!$B$2+G9-H9-Settings!$B$3),"") | K9: =IF(OR(LEFT(L9,9)="ORDER NOW",L9="Order this week"),MAX(0,CEILING((H9+Settings!$B$3+Settings!$B$4)*C9-D9-E9,10)),0) | L9: =IF(G9-H9-Settings!$B$3<=0,IF(F9<H9,"ORDER NOW: stockout risk","ORDER NOW"),IF(G9-H9-Settings!$B$3<=7,"Order this week",IF(G9>Settings!$B$5,"Overstock",IF(F9<H9,"Low FBA, inbound covers","OK"))))
A10: HP-SIL-LID6 | B10: Silicone Stretch Lids, 6-Pack Assorted Sizes | C10: ='Profit by SKU'!D3/Settings!$B$1 | D10: 2400 | E10: 0 | F10: =IFERROR(D10/C10,999) | G10: =IFERROR((D10+E10)/C10,999) | H10: 40 | I10: =IFERROR(Settings!$B$2+D10/C10,"") | J10: =IFERROR(MAX(Settings!$B$2,Settings!$B$2+G10-H10-Settings!$B$3),"") | K10: =IF(OR(LEFT(L10,9)="ORDER NOW",L10="Order this week"),MAX(0,CEILING((H10+Settings!$B$3+Settings!$B$4)*C10-D10-E10,10)),0) | L10: =IF(G10-H10-Settings!$B$3<=0,IF(F10<H10,"ORDER NOW: stockout risk","ORDER NOW"),IF(G10-H10-Settings!$B$3<=7,"Order this week",IF(G10>Settings!$B$5,"Overstock",IF(F10<H10,"Low FBA, inbound covers","OK"))))
A11: HP-SS-STRW8 | B11: Stainless Steel Straws, 8-Pack with Brushes | C11: ='Profit by SKU'!D5/Settings!$B$1 | D11: 1900 | E11: 0 | F11: =IFERROR(D11/C11,999) | G11: =IFERROR((D11+E11)/C11,999) | H11: 40 | I11: =IFERROR(Settings!$B$2+D11/C11,"") | J11: =IFERROR(MAX(Settings!$B$2,Settings!$B$2+G11-H11-Settings!$B$3),"") | K11: =IF(OR(LEFT(L11,9)="ORDER NOW",L11="Order this week"),MAX(0,CEILING((H11+Settings!$B$3+Settings!$B$4)*C11-D11-E11,10)),0) | L11: =IF(G11-H11-Settings!$B$3<=0,IF(F11<H11,"ORDER NOW: stockout risk","ORDER NOW"),IF(G11-H11-Settings!$B$3<=7,"Order this week",IF(G11>Settings!$B$5,"Overstock",IF(F11<H11,"Low FBA, inbound covers","OK"))))
A12: HP-HRB-KEEP | B12: Herb Keeper Fresh Saver, Clear | C12: ='Profit by SKU'!D13/Settings!$B$1 | D12: 720 | E12: 0 | F12: =IFERROR(D12/C12,999) | G12: =IFERROR((D12+E12)/C12,999) | H12: 45 | I12: =IFERROR(Settings!$B$2+D12/C12,"") | J12: =IFERROR(MAX(Settings!$B$2,Settings!$B$2+G12-H12-Settings!$B$3),"") | K12: =IF(OR(LEFT(L12,9)="ORDER NOW",L12="Order this week"),MAX(0,CEILING((H12+Settings!$B$3+Settings!$B$4)*C12-D12-E12,10)),0) | L12: =IF(G12-H12-Settings!$B$3<=0,IF(F12<H12,"ORDER NOW: stockout risk","ORDER NOW"),IF(G12-H12-Settings!$B$3<=7,"Order this week",IF(G12>Settings!$B$5,"Overstock",IF(F12<H12,"Low FBA, inbound covers","OK"))))
A13: HP-CRM-MUG2 | B13: Ceramic Coffee Mugs 16oz, Set of 2 | C13: ='Profit by SKU'!D12/Settings!$B$1 | D13: 900 | E13: 0 | F13: =IFERROR(D13/C13,999) | G13: =IFERROR((D13+E13)/C13,999) | H13: 60 | I13: =IFERROR(Settings!$B$2+D13/C13,"") | J13: =IFERROR(MAX(Settings!$B$2,Settings!$B$2+G13-H13-Settings!$B$3),"") | K13: =IF(OR(LEFT(L13,9)="ORDER NOW",L13="Order this week"),MAX(0,CEILING((H13+Settings!$B$3+Settings!$B$4)*C13-D13-E13,10)),0) | L13: =IF(G13-H13-Settings!$B$3<=0,IF(F13<H13,"ORDER NOW: stockout risk","ORDER NOW"),IF(G13-H13-Settings!$B$3<=7,"Order this week",IF(G13>Settings!$B$5,"Overstock",IF(F13<H13,"Low FBA, inbound covers","OK"))))

Sheet Settings
A1: Report period, days | B1: 30
A2: As-of date | B2: 46301
A3: Safety stock, days | B3: 14
A4: Target cover after arrival, days | B4: 60
A5: Overstock above, days of cover | B5: 120
A6: Low conversion below | B6: 0.08
A7: …with sessions above | B7: 2000
A9: Yellow cells on every sheet are inputs. Change them and all numbers recalculate.
